colorful/__init__.py
colorful/fields.py
colorful/forms.py
colorful/models.py
colorful/widgets.py
colorful/static/colorful/arrow.gif
colorful/static/colorful/colorPicker.css
colorful/static/colorful/jQuery.colorPicker.js
django_colorful-1.4.0.dist-info/licenses/AUTHORS
django_colorful-1.4.0.dist-info/licenses/LICENSE
django_colorful-1.4.0.dist-info/METADATA
django_colorful-1.4.0.dist-info/WHEEL
django_colorful-1.4.0.dist-info/top_level.txt
django_colorful-1.4.0.dist-info/RECORD
